<?xml version='1.0' encoding='utf-8'?>
<PARAMMETA XmlVersion="0">
    <Field>
        <weaponId AltName="Weapon ID" />
        <weaponModelId AltName="Weapon model ID" />
        <weaponReinforceId AltName="Weapon growth settings" />
        <weaponActionCategoryId AltName="Weapon action category settings" />
        <weaponTypeId AltName="weapon type" Refs="WeaponTypeParam" />
        <isAtkAutoHoming AltName="Proximity autohoming" IsBool="true" />
        <weaponCategory AltName="Weapon system" ProjectEnum="WEAPON_SIMPLE_CATEGORY" />
        <clothCollidableId AltName="Cross collision ID" />
        <requiredStrength AltName="Required status Strength" />
        <requiredDexterity AltName="Required status Skill" />
        <requiredIntelligence AltName="Required status Reason" />
        <requiredFaith AltName="Required status Faith" />
        <weight AltName="Parameter weight [kg]" />
        <adjustBalanceWeight AltName="Parameter Distributed weight [kg]" />
        <durability AltName="Parameter durability value" />
        <repairCost AltName="Parameter Repair cost [soul]" />
        <materialId AltName="Parameter material" ProjectEnum="MATERIAL_TYPE_ENUM" />
        <meleeAttackBaseCost AltName="Attack consumption stamina Melee attack base value" />
        <rangedAttackBaseCost AltName="Attack consumption stamina Shooting attack base value" />
        <costCategoryId AltName="Attack consumption stamina multiplier category" Refs="WeaponStaminaCostParam" />
        <lockonAvailableDistanceScale AltName="Lock-on attack effective distance correction magnification [x]" />
        <grabMotionRate AltName="Throw grab playback magnification [x]" />
        <grabRotationSpeed AltName="Throw and grab turning acceleration [deg/sec]" />
        <grabRotationMaxSpeed AltName="Throw grab maximum turning speed [deg/sec]" />
        <backStabAttackDamageSmallId AltName="Throw grab Backstab throw grab [Small] Damage ID" />
        <backStabAttackDamageMiddleId AltName="Throw grab Backstab throw grab [Medium] Damage ID" />
        <backStabAttackDamageLargeId AltName="Throw grab Backstab throw grab [Large] Damage ID" />
        <gdBreakStabAttackDamageSmallId AltName="Throw Grasp Guard Break Stab Throw Grasp [Small] Damage ID" />
        <gdBreakStabAttackDamageMiddleId AltName="Throw Grasp Guard Break Stab Throw Grasp [Medium] Damage ID" />
        <gdBreakStabAttackDamageLargeId AltName="Throw Grasp Guard Break Stab Throw Grasp [Large] Damage ID" />
        <parryStabAttackDamageSmallId AltName="Throw Grab Parry Break Stab Throw Grab [Small] Damage ID" />
        <parryStabAttackDamageMiddleId AltName="Throw Grab Parry Break Stab Throw Grab [Medium] Damage ID" />
        <parryStabAttackDamageLargeId AltName="Throw Grab Parry Break Stab Throw Grab [Large] Damage ID" />
        <parryEnableRate AltName="Parry occurrence period Effective rate" />
        <brokenSfxId AltName="Weapon damage SFXID" />
        <brokenSoundType AltName="Weapon damage sound type" ProjectEnum="EQUIP_BREAK_SOUND_MATERIAL_TYPE" />
        <damageScale AltName="Damage multiplier" />
        <staminaDamageScale AltName="Stamina taken amount multiplier" />
        <durabilityDamageScale AltName="Durability machining value magnification" />
        <ignorePoiseRateScale AltName="Toughness invalidation ratio Multiplier" />
        <ignoreDamageCutRateScale AltName="Shield cut rate invalidation rate magnification" />
        <stunDamageScale AltName="Faint value magnification" />
        <damageHitRadiusScale AltName="HIT radius magnification" />
        <damageHitLengthScale AltName="HIT length magnification" />
        <recoilHitRaduisScale AltName="Hit radius magnification" />
        <recoilHitLengthScale AltName="Play HIT length magnification" />
        <menuAttackCategory1 AltName="Attack attribute 1 for menu" ProjectEnum="WEAPON_ATTACK_CATEGORY" />
        <menuAttackCategory2 AltName="Attack attribute 2 for menu" ProjectEnum="WEAPON_ATTACK_CATEGORY" />
        <menuPoiseDamage AltName="Tough cutting value for menu" />
        <menuCounterScale AltName="Counter correction value for menu" />
        <menuSpellChantSpeed AltName="Spell casting speed for menu" />
        <poiseDamageScalePlayer AltName="Strong machining value correction magnification (vs. players)" />
        <poiseDamageScaleEnemy AltName="Strong machining value correction magnification (against enemy)" />
        <uninterruptibleRate AltName="Uninterruptible poise damage rate" />
    </Field>
</PARAMMETA>
