<?xml version='1.0' encoding='utf-8'?>
<PARAMDEF XmlVersion="0">
    <ParamType>DAMAGE_EFFECT_MATERIAL_PARAM</ParamType>
    <DataVersion>4</DataVersion>
    <BigEndian>true</BigEndian>
    <Unicode>true</Unicode>
    <FormatVersion>105</FormatVersion>
    <Fields>
        <Field Def="u32 bodyEffect01" />
        <Field Def="u32 bodyEffect02" />
        <Field Def="u8 bodySize01" />
        <Field Def="u8 bodySize02" />
        <Field Def="dummy8 bodyDummy[2]" />
        <Field Def="u32 petrifiedBossBodyEffect01" />
        <Field Def="u32 petrifiedBossBodyEffect02" />
        <Field Def="u8 petrifiedBossBodySize01" />
        <Field Def="u8 petrifiedBossBodySize02" />
        <Field Def="dummy8 petrifiedBossBodyDummy[2]" />
        <Field Def="u32 noneEffect01" />
        <Field Def="u32 noneEffect02" />
        <Field Def="u8 noneSize01" />
        <Field Def="u8 noneSize02" />
        <Field Def="dummy8 noneDummy[2]" />
        <Field Def="u32 metalEffect01" />
        <Field Def="u32 metalEffect02" />
        <Field Def="u8 metalSize01" />
        <Field Def="u8 metalSize02" />
        <Field Def="dummy8 metalDummy[2]" />
        <Field Def="u32 heavymetalEffect01" />
        <Field Def="u32 heavymetalEffect02" />
        <Field Def="u8 heavymetalSize01" />
        <Field Def="u8 heavymetalSize02" />
        <Field Def="dummy8 heavymetalDummy[2]" />
        <Field Def="u32 woodEffect01" />
        <Field Def="u32 woodEffect02" />
        <Field Def="u8 woodSize01" />
        <Field Def="u8 woodSize02" />
        <Field Def="dummy8 woodDummy[2]" />
        <Field Def="u32 waterEffect01" />
        <Field Def="u32 waterEffect02" />
        <Field Def="u8 waterSize01" />
        <Field Def="u8 waterSize02" />
        <Field Def="dummy8 waterDummy[2]" />
        <Field Def="u32 swampEffect01" />
        <Field Def="u32 swampEffect02" />
        <Field Def="u8 swampSize01" />
        <Field Def="u8 swampSize02" />
        <Field Def="dummy8 swampDummy[2]" />
        <Field Def="u32 lumberEffect01" />
        <Field Def="u32 lumberEffect02" />
        <Field Def="u8 lumberSize01" />
        <Field Def="u8 lumberSize02" />
        <Field Def="dummy8 lumberDummy[2]" />
        <Field Def="u32 meatEffect01" />
        <Field Def="u32 meatEffect02" />
        <Field Def="u8 meatSize01" />
        <Field Def="u8 meatSize02" />
        <Field Def="dummy8 meatDummy[2]" />
        <Field Def="u32 deadmeatEffect01" />
        <Field Def="u32 deadmeatEffect02" />
        <Field Def="u8 deadmeatSize01" />
        <Field Def="u8 deadmeatSize02" />
        <Field Def="dummy8 deadmeatDummy[2]" />
        <Field Def="u32 insectEffect01" />
        <Field Def="u32 insectEffect02" />
        <Field Def="u8 insectSize01" />
        <Field Def="u8 insectSize02" />
        <Field Def="dummy8 insectDummy[2]" />
        <Field Def="u32 giantEffect01" />
        <Field Def="u32 giantEffect02" />
        <Field Def="u8 giantSize01" />
        <Field Def="u8 giantSize02" />
        <Field Def="dummy8 giantDummy[2]" />
        <Field Def="u32 boneEffect01" />
        <Field Def="u32 boneEffect02" />
        <Field Def="u8 boneSize01" />
        <Field Def="u8 boneSize02" />
        <Field Def="dummy8 boneDummy[2]" />
        <Field Def="u32 copperEffect01" />
        <Field Def="u32 copperEffect02" />
        <Field Def="u8 copperSize01" />
        <Field Def="u8 copperSize02" />
        <Field Def="dummy8 copperDummy[2]" />
        <Field Def="u32 energyEffect01" />
        <Field Def="u32 energyEffect02" />
        <Field Def="u8 energySize01" />
        <Field Def="u8 energySize02" />
        <Field Def="dummy8 energyDummy[2]" />
        <Field Def="u32 fireEffect01" />
        <Field Def="u32 fireEffect02" />
        <Field Def="u8 fireSize01" />
        <Field Def="u8 fireSize02" />
        <Field Def="dummy8 fireDummy[2]" />
        <Field Def="u32 thunderEffect01" />
        <Field Def="u32 thunderEffect02" />
        <Field Def="u8 thunderSize01" />
        <Field Def="u8 thunderSize02" />
        <Field Def="dummy8 thunderDummy[2]" />
        <Field Def="u32 darkEffect01" />
        <Field Def="u32 darkEffect02" />
        <Field Def="u8 darkSize01" />
        <Field Def="u8 darkSize02" />
        <Field Def="dummy8 darkDummy[2]" />
        <Field Def="u32 magicEffect01" />
        <Field Def="u32 magicEffect02" />
        <Field Def="u8 magicSize01" />
        <Field Def="u8 magicSize02" />
        <Field Def="dummy8 magicDummy[2]" />
        <Field Def="u32 stoneEffect01" />
        <Field Def="u32 stoneEffect02" />
        <Field Def="u8 stoneSize01" />
        <Field Def="u8 stoneSize02" />
        <Field Def="dummy8 stoneDummy[2]" />
        <Field Def="u32 dirtEffect01" />
        <Field Def="u32 dirtEffect02" />
        <Field Def="u8 dirtSize01" />
        <Field Def="u8 dirtSize02" />
        <Field Def="dummy8 dirtDummy[2]" />
        <Field Def="u32 carpetEffect01" />
        <Field Def="u32 carpetEffect02" />
        <Field Def="u8 carpetSize01" />
        <Field Def="u8 carpetSize02" />
        <Field Def="dummy8 carpetDummy[2]" />
        <Field Def="u32 grassEffect01" />
        <Field Def="u32 grassEffect02" />
        <Field Def="u8 grassSize01" />
        <Field Def="u8 grassSize02" />
        <Field Def="dummy8 grassDummy[2]" />
        <Field Def="u32 gravelEffect01" />
        <Field Def="u32 gravelEffect02" />
        <Field Def="u8 gravelSize01" />
        <Field Def="u8 gravelSize02" />
        <Field Def="dummy8 gravelDummy[2]" />
        <Field Def="u32 clothEffect01" />
        <Field Def="u32 clothEffect02" />
        <Field Def="u8 clothSize01" />
        <Field Def="u8 clothSize02" />
        <Field Def="dummy8 clothDummy[2]" />
        <Field Def="u32 sandEffect01" />
        <Field Def="u32 sandEffect02" />
        <Field Def="u8 sandSize01" />
        <Field Def="u8 sandSize02" />
        <Field Def="dummy8 sandDummy[2]" />
        <Field Def="u32 ashEffect01" />
        <Field Def="u32 ashEffect02" />
        <Field Def="u8 ashSize01" />
        <Field Def="u8 ashSize02" />
        <Field Def="dummy8 ashDummy[2]" />
        <Field Def="u32 poisonswampEffect01" />
        <Field Def="u32 poisonswampEffect02" />
        <Field Def="u8 poisonswampSize01" />
        <Field Def="u8 poisonswampSize02" />
        <Field Def="dummy8 poisonswampDummy[2]" />
        <Field Def="u32 oilEffect01" />
        <Field Def="u32 oilEffect02" />
        <Field Def="u8 oilSize01" />
        <Field Def="u8 oilSize02" />
        <Field Def="dummy8 oilDummy[2]" />
        <Field Def="u32 coaltarEffect01" />
        <Field Def="u32 coaltarEffect02" />
        <Field Def="u8 coaltarSize01" />
        <Field Def="u8 coaltarSize02" />
        <Field Def="dummy8 coaltarDummy[2]" />
        <Field Def="u32 lavaEffect01" />
        <Field Def="u32 lavaEffect02" />
        <Field Def="u8 lavaSize01" />
        <Field Def="u8 lavaSize02" />
        <Field Def="dummy8 lavaDummy[2]" />
        <Field Def="u32 stringEffect01" />
        <Field Def="u32 stringEffect02" />
        <Field Def="u8 stringSize01" />
        <Field Def="u8 stringSize02" />
        <Field Def="dummy8 stringDummy[2]" />
        <Field Def="u32 sulfurcrystalEffect01" />
        <Field Def="u32 sulfurcrystalEffect02" />
        <Field Def="u8 sulfurcrystalSize01" />
        <Field Def="u8 sulfurcrystalSize02" />
        <Field Def="dummy8 sulfurcrystalDummy[2]" />
        <Field Def="u32 soulEffect01" />
        <Field Def="u32 soulEffect02" />
        <Field Def="u8 soulSize01" />
        <Field Def="u8 soulSize02" />
        <Field Def="dummy8 soulDummy[2]" />
        <Field Def="u32 frogEffect01" />
        <Field Def="u32 frogEffect02" />
        <Field Def="u8 frogSize01" />
        <Field Def="u8 frogSize02" />
        <Field Def="dummy8 frogDummy[2]" />
        <Field Def="u32 stoneWaterEffect01" />
        <Field Def="u32 stoneWaterEffect02" />
        <Field Def="u8 stoneWaterSize01" />
        <Field Def="u8 stoneWaterSize02" />
        <Field Def="dummy8 stoneWaterDummy[2]" />
        <Field Def="u32 stoneEnergyEffect01" />
        <Field Def="u32 stoneEnergyEffect02" />
        <Field Def="u8 stoneEnergySize01" />
        <Field Def="u8 stoneEnergySize02" />
        <Field Def="dummy8 stoneEnergyDummy[2]" />
        <Field Def="u32 coverEffect01" />
        <Field Def="u32 coverEffect02" />
        <Field Def="u8 coverSize01" />
        <Field Def="u8 coverSize02" />
        <Field Def="dummy8 coverDummy[2]" />
        <Field Def="u32 unkMat0Effect01" />
        <Field Def="u32 unkMat0Effect02" />
        <Field Def="u8 unkMat0Size01" />
        <Field Def="u8 unkMat0Size02" />
        <Field Def="dummy8 unkMat0Dummy[2]" />
        <Field Def="u32 unkMat1Effect01" />
        <Field Def="u32 unkMat1Effect02" />
        <Field Def="u8 unkMat1Size01" />
        <Field Def="u8 unkMat1Size02" />
        <Field Def="dummy8 unkMat1Dummy[2]" />
        <Field Def="u32 unkMat2Effect01" />
        <Field Def="u32 unkMat2Effect02" />
        <Field Def="u8 unkMat2Size01" />
        <Field Def="u8 unkMat2Size02" />
        <Field Def="dummy8 unkMat2Dummy[2]" />
        <Field Def="u32 unkMat3Effect01" />
        <Field Def="u32 unkMat3Effect02" />
        <Field Def="u8 unkMat3Size01" />
        <Field Def="u8 unkMat3Size02" />
        <Field Def="dummy8 unkMat3Dummy[2]" />
        <Field Def="u32 unkMat4Effect01" />
        <Field Def="u32 unkMat4Effect02" />
        <Field Def="u8 unkMat4Size01" />
        <Field Def="u8 unkMat4Size02" />
        <Field Def="dummy8 unkMat4Dummy[2]" />
        <Field Def="u32 unkMat5Effect01" />
        <Field Def="u32 unkMat5Effect02" />
        <Field Def="u8 unkMat5Size01" />
        <Field Def="u8 unkMat5Size02" />
        <Field Def="dummy8 unkMat5Dummy[2]" />
        <Field Def="u32 unkMat6Effect01" />
        <Field Def="u32 unkMat6Effect02" />
        <Field Def="u8 unkMat6Size01" />
        <Field Def="u8 unkMat6Size02" />
        <Field Def="dummy8 unkMat6Dummy[2]" />
        <Field Def="u32 unkMat7Effect01" />
        <Field Def="u32 unkMat7Effect02" />
        <Field Def="u8 unkMat7Size01" />
        <Field Def="u8 unkMat7Size02" />
        <Field Def="dummy8 unkMat7Dummy[2]" />
        <Field Def="u32 unkMat8Effect01" />
        <Field Def="u32 unkMat8Effect02" />
        <Field Def="u8 unkMat8Size01" />
        <Field Def="u8 unkMat8Size02" />
        <Field Def="dummy8 unkMat8Dummy[2]" />
    </Fields>
</PARAMDEF>
