<?xml version='1.0' encoding='utf-8'?>
<PARAMDEF XmlVersion="0">
    <ParamType>MAP_OBJECT_GD_PARAM</ParamType>
    <DataVersion>3</DataVersion>
    <BigEndian>true</BigEndian>
    <Unicode>true</Unicode>
    <FormatVersion>105</FormatVersion>
    <Fields>
        <Field Def="s32 animId" />
        <Field Def="u16 initialFrameHead" />
        <Field Def="u16 initialFrameTail" />
        <Field Def="u8 isLoopAnim" />
        <Field Def="u8 isBreakable:1" />
        <Field Def="u8 isPrefab:1" />
        <Field Def="u8 cameraHit" />
        <Field Def="u8 emissiveScale0" />
        <Field Def="u8 emissiveScale1" />
        <Field Def="dummy8 pad2[3]" />
        <Field Def="s32 sfxId0" />
        <Field Def="s32 sfxId1" />
        <Field Def="s32 sfxId2" />
        <Field Def="s32 sfxId3" />
        <Field Def="s32 sfxId4" />
        <Field Def="s32 sfxId5" />
        <Field Def="s32 sfxIdBreak0" />
        <Field Def="u8 sfxPoint0" />
        <Field Def="u8 sfxPoint1" />
        <Field Def="u8 sfxPoint2" />
        <Field Def="u8 sfxPoint3" />
        <Field Def="u8 sfxPoint4" />
        <Field Def="u8 sfxPoint5" />
        <Field Def="u8 sfxPointBreak0" />
        <Field Def="u8 sfxDmyPolyId0" />
        <Field Def="u8 sfxDmyPolyId1" />
        <Field Def="u8 sfxDmyPolyId2" />
        <Field Def="u8 sfxDmyPolyId3" />
        <Field Def="u8 sfxDmyPolyId4" />
        <Field Def="u8 sfxDmyPolyId5" />
        <Field Def="u8 sfxDmyPolyIdBreak0" />
        <Field Def="u8 doesFollow0" />
        <Field Def="u8 doesFollow1" />
        <Field Def="u8 doesFollow2" />
        <Field Def="u8 doesFollow3" />
        <Field Def="u8 doesFollow4" />
        <Field Def="u8 doesFollow5" />
    </Fields>
</PARAMDEF>
