<?xml version='1.0' encoding='utf-8'?>
<PARAMDEF XmlVersion="0">
    <ParamType>DAMAGE_MOTION_WEIGHT_PARAM</ParamType>
    <DataVersion>1</DataVersion>
    <BigEndian>true</BigEndian>
    <Unicode>true</Unicode>
    <FormatVersion>104</FormatVersion>
    <Fields>
        <Field Def="u8 noneSize" />
        <Field Def="u8 superSmallSize" />
        <Field Def="u8 smallSize" />
        <Field Def="u8 normalSize" />
        <Field Def="u8 largeSize" />
        <Field Def="u8 superLargeSize" />
        <Field Def="u8 hyperLargeSize" />
        <Field Def="u8 ultraLargeSize" />
    </Fields>
</PARAMDEF>
